Workbook

Sheet Master Task Tracker
A1: LONDON CONTENT CHANNELS — Master Launch Tracker
A2: Phase | B2: Task ID | C2: Task Description | D2: Owner | E2: Deadline | F2: Status | G2: Priority | H2: % Complete | I2: Notes / Automation
A3: Phase 1 | B3: 1.1.1 | C3: Register all social accounts for LondonIn&Out (TikTok, IG, YT, FB, X) | D3: Founder | E3: Week 1 | F3: Not Started | G3: HIGH | H3: 0 | I3: Use Namechk for handle availability check
A4: Phase 1 | B4: 1.1.2 | C4: Commission London Fox AI character design | D4: Founder | E4: Week 1 | F4: Not Started | G4: HIGH | H4: 0 | I4: Midjourney batch generation or Fiverr brief template
A5: Phase 1 | B5: 1.1.3 | C5: Purchase equipment (gimbal £79, mic £99) | D5: Founder | E5: Week 1 | F5: Not Started | G5: HIGH | H5: 0 | I5: Amazon auto-buy list
A6: Phase 1 | B6: 1.1.4 | C6: Set up CapCut templates for IN/OUT split-screen format | D6: Editor | E6: Week 1 | F6: Not Started | G6: HIGH | H6: 0 | I6: Create 3-5 reusable templates
A7: Phase 1 | B7: 1.1.5 | C7: Set up ElevenLabs AI voice for London Fox | D7: Founder | E7: Week 1 | F7: Not Started | G7: MEDIUM | H7: 0 | I7: API integration for batch voiceover
A8: Phase 1 | B8: 1.1.6 | C8: Create content calendar (Notion/Airtable) | D8: Founder | E8: Week 1 | F8: Not Started | G8: MEDIUM | H8: 0 | I8: Template with cross-platform scheduling
A9: Phase 1 | B9: 1.1.7 | C9: Subscribe to X Premium for In&Out (£8/mo) | D9: Founder | E9: Week 1 | F9: Not Started | G9: LOW | H9: 0 | I9: Recurring payment setup
A10: Phase 1 | B10: 1.1.8 | C10: Set up cross-posting tools (Later/Buffer/Repurpose.io) | D10: Founder | E10: Week 1 | F10: Not Started | G10: MEDIUM | H10: 0 | I10: 1 upload → auto-push to all platforms
A11: Phase 1 | B11: 1.2.1 | C11: Film first IN/OUT content batch (10-15 videos) | D11: Founder | E11: Week 2 | F11: Not Started | G11: HIGH | H11: 0 | I11: Shot list from trending London topics
A12: Phase 1 | B12: 1.2.2 | C12: Edit and publish first 5 TikToks + IG Reels | D12: Editor | E12: Week 2 | F12: Not Started | G12: HIGH | H12: 0 | I12: CapCut batch export per platform
A13: Phase 1 | B13: 1.2.3 | C13: Begin daily X hot takes and IN/OUT polls | D13: Founder | E13: Week 2 | F13: Not Started | G13: HIGH | H13: 0 | I13: Scheduled tweet queue via Buffer
A14: Phase 1 | B14: 1.2.4 | C14: Repurpose content to Facebook (native, no watermark) | D14: Editor | E14: Week 2 | F14: Not Started | G14: MEDIUM | H14: 0 | I14: Auto-strip watermarks; batch upload
... A45: Phase 4 | B45: 4.9 | C45: Set up accounting (FreeAgent/Xero) | D45: Founder | E45: Month 4 | F45: Not Started | G45: HIGH | H45: 0 | I45: Auto-categorise + receipt scanning

Sheet Dashboard
A1: LAUNCH DASHBOARD — Progress Overview
A3: Metric | B3: Phase 1 | C3: Phase 2 | D3: Phase 3 | E3: Phase 4 | F3: TOTAL
A4: Total Tasks | B4: =COUNTIF('Master Task Tracker'!A3:A45,"Phase 1") -> 16 | C4: =COUNTIF('Master Task Tracker'!A3:A45,"Phase 2") -> 10 | D4: =COUNTIF('Master Task Tracker'!A3:A45,"Phase 3") -> 8 | E4: =COUNTIF('Master Task Tracker'!A3:A45,"Phase 4") -> 9 | F4: =SUM(B4:E4) -> 43
A5: Complete | B5: =COUNTIFS('Master Task Tracker'!A3:A45,"Phase 1",'Master Task Tracker'!F3:F45,"Complete") -> 0 | C5: =COUNTIFS('Master Task Tracker'!A3:A45,"Phase 2",'Master Task Tracker'!F3:F45,"Complete") -> 0 | D5: =COUNTIFS('Master Task Tracker'!A3:A45,"Phase 3",'Master Task Tracker'!F3:F45,"Complete") -> 0 | E5: =COUNTIFS('Master Task Tracker'!A3:A45,"Phase 4",'Master Task Tracker'!F3:F45,"Complete") -> 0 | F5: =SUM(B5:E5) -> 0
A6: In Progress | B6: =COUNTIFS('Master Task Tracker'!A3:A45,"Phase 1",'Master Task Tracker'!F3:F45,"In Progress") -> 0 | C6: =COUNTIFS('Master Task Tracker'!A3:A45,"Phase 2",'Master Task Tracker'!F3:F45,"In Progress") -> 0 | D6: =COUNTIFS('Master Task Tracker'!A3:A45,"Phase 3",'Master Task Tracker'!F3:F45,"In Progress") -> 0 | E6: =COUNTIFS('Master Task Tracker'!A3:A45,"Phase 4",'Master Task Tracker'!F3:F45,"In Progress") -> 0 | F6: =SUM(B6:E6) -> 0
A7: Not Started | B7: =COUNTIFS('Master Task Tracker'!A3:A45,"Phase 1",'Master Task Tracker'!F3:F45,"Not Started") -> 16 | C7: =COUNTIFS('Master Task Tracker'!A3:A45,"Phase 2",'Master Task Tracker'!F3:F45,"Not Started") -> 10 | D7: =COUNTIFS('Master Task Tracker'!A3:A45,"Phase 3",'Master Task Tracker'!F3:F45,"Not Started") -> 8 | E7: =COUNTIFS('Master Task Tracker'!A3:A45,"Phase 4",'Master Task Tracker'!F3:F45,"Not Started") -> 9 | F7: =SUM(B7:E7) -> 43
A8: Blocked | B8: =COUNTIFS('Master Task Tracker'!A3:A45,"Phase 1",'Master Task Tracker'!F3:F45,"Blocked") -> 0 | C8: =COUNTIFS('Master Task Tracker'!A3:A45,"Phase 2",'Master Task Tracker'!F3:F45,"Blocked") -> 0 | D8: =COUNTIFS('Master Task Tracker'!A3:A45,"Phase 3",'Master Task Tracker'!F3:F45,"Blocked") -> 0 | E8: =COUNTIFS('Master Task Tracker'!A3:A45,"Phase 4",'Master Task Tracker'!F3:F45,"Blocked") -> 0 | F8: =SUM(B8:E8) -> 0
A9: % Complete | B9: =IF(B4>0,B5/B4,0) -> 0 | C9: =IF(C4>0,C5/C4,0) -> 0 | D9: =IF(D4>0,D5/D4,0) -> 0 | E9: =IF(E4>0,E5/E4,0) -> 0 | F9: =IF(F4>0,F5/F4,0) -> 0

Sheet Budget Tracker
A1: BUDGET & EXPENSE TRACKER
A3: Category | B3: Item | C3: Budget (£) | D3: Actual (£) | E3: Variance (£) | F3: Status
A4: Equipment | B4: Camera (smartphone/Sony ZV-1F) | C4: 0 | D4: 0 | E4: =C4-D4 -> 0 | F4: =IF(D4=0,"Pending",IF(D4<=C4,"On Budget","Over Budget")) -> Pending
A5: Equipment | B5: DJI Osmo Mobile SE gimbal | C5: 79 | D5: 0 | E5: =C5-D5 -> 79 | F5: =IF(D5=0,"Pending",IF(D5<=C5,"On Budget","Over Budget")) -> Pending
A6: Equipment | B6: Rode Wireless ME microphone | C6: 99 | D6: 0 | E6: =C6-D6 -> 99 | F6: =IF(D6=0,"Pending",IF(D6<=C6,"On Budget","Over Budget")) -> Pending
A7: Software | B7: CapCut (free) / Adobe Premiere | C7: 0 | D7: 0 | E7: =C7-D7 -> 0 | F7: =IF(D7=0,"Pending",IF(D7<=C7,"On Budget","Over Budget")) -> Pending
A8: Software | B8: Midjourney subscription (£8/mo x 12) | C8: 96 | D8: 0 | E8: =C8-D8 -> 96 | F8: =IF(D8=0,"Pending",IF(D8<=C8,"On Budget","Over Budget")) -> Pending
A9: Software | B9: Canva Pro (£10/mo x 12) | C9: 120 | D9: 0 | E9: =C9-D9 -> 120 | F9: =IF(D9=0,"Pending",IF(D9<=C9,"On Budget","Over Budget")) -> Pending
A10: Software | B10: ElevenLabs AI voice (£5/mo x 12) | C10: 60 | D10: 0 | E10: =C10-D10 -> 60 | F10: =IF(D10=0,"Pending",IF(D10<=C10,"On Budget","Over Budget")) -> Pending
A11: Platform | B11: X Premium x4 accounts (£32/mo x 12) | C11: 384 | D11: 0 | E11: =C11-D11 -> 384 | F11: =IF(D11=0,"Pending",IF(D11<=C11,"On Budget","Over Budget")) -> Pending
A12: AI Characters | B12: Character design (Fox, Goat, Dark Goat) | C12: 300 | D12: 0 | E12: =C12-D12 -> 300 | F12: =IF(D12=0,"Pending",IF(D12<=C12,"On Budget","Over Budget")) -> Pending
A13: Content | B13: Cross-posting tool (Later/Buffer, £15/mo x 10) | C13: 150 | D13: 0 | E13: =C13-D13 -> 150 | F13: =IF(D13=0,"Pending",IF(D13<=C13,"On Budget","Over Budget")) -> Pending
A14: Content | B14: Freelance editor (Month 7-12, £1,000/mo x 6) | C14: 6000 | D14: 0 | E14: =C14-D14 -> 6000 | F14: =IF(D14=0,"Pending",IF(D14<=C14,"On Budget","Over Budget")) -> Pending
A15: Business | B15: HMRC registration / accountant | C15: 200 | D15: 0 | E15: =C15-D15 -> 200 | F15: =IF(D15=0,"Pending",IF(D15<=C15,"On Budget","Over Budget")) -> Pending
... A18: Marketing | B18: Newsletter platform (Beehiiv free tier) | C18: 0 | D18: 0 | E18: =C18-D18 -> 0 | F18: =IF(D18=0,"Pending",IF(D18<=C18,"On Budget","Over Budget")) -> Pending
B19: TOTAL | C19: =SUM(C4:C18) -> 7732 | D19: =SUM(D4:D18) -> 0 | E19: =C19-D19 -> 7732

Sheet Content Calendar
A1: WEEKLY CONTENT CALENDAR TEMPLATE
A3: Day | B3: Channel | C3: Platform | D3: Format | E3: Topic / Hook | F3: Status | G3: Scheduled Time | H3: Performance Notes
A4: Monday | B4: LondonIn&Out | C4: TikTok | D4: IN/OUT Reel (60-90s) | F4: Draft
A5: Monday | B5: LondonIn&Out | C5: X/Twitter | D5: Hot Take Tweet + Poll | F5: Draft
A6: Monday | B6: LondonGoat | C6: TikTok | D6: Street Scene Reel (15-60s) | F6: Draft
A7: Monday | B7: BlackGoat (X) | C7: X/Twitter | D7: News Commentary Tweet | F7: Draft
A8: Tuesday | B8: LondonIn&Out | C8: Instagram | D8: IN/OUT Carousel (5 slides) | F8: Draft
A9: Tuesday | B9: LondonGoat | C9: TikTok | D9: London Walk Reel | F9: Draft
A10: Tuesday | B10: LondonGoat | C10: Instagram Stories | D10: Behind-the-scenes Story | F10: Draft
A11: Wednesday | B11: LondonIn&Out | C11: TikTok | D11: IN/OUT Reel | F11: Draft
A12: Wednesday | B12: LondonIn&Out | C12: Facebook | D12: IN/OUT Reel (native upload) | F12: Draft
A13: Wednesday | B13: BlackGoat | C13: TikTok | D13: BlackGoat Reads Papers Reel | F13: Draft
A14: Wednesday | B14: PeoplesofLondon | C14: Instagram | D14: Portrait + Long Caption | F14: Draft
A15: Thursday | B15: LondonGoat | C15: TikTok | D15: Street Scene Reel | F15: Draft
... A25: Sunday | B25: BlackGoat (X) | C25: X/Twitter Thread | D25: Weekly News Round-up Thread | F25: Draft
